ps3/ps03q/traffic_light_controller.v
///////////////////////////////////////////////////////////////// 
// Author - Imants Pulkstenis
// Date - 23.02.2020
// Project name - PS03
// Module name - Smart traffic light controler
//
// Detailed module description:
//
// Task is to develop a Smart Traffic Light Controller VHDL(Verilog) 
// module using finite state machine principle (FSM).  
// 
// Port description  
// | Port name  | Direction  | Description                                                                                                              |
// |------------|------------|--------------------------------------------------------------------------------------------------------------------------|
// | Clk        | In         | 1 GHz clock (1 ns period)                                                                                                |
// | Rst        | In         | Active low reset                                                                                                         |
// | MR_cars    | In         | An 8-bit input signal indicating the number of waiting cars at the secondary road traffic light. Interpret as unsigned.  |
// | MR_ctl     | Out        | Main road traffic light controlling signal                                                                               |
// | SR_ctl     | Out        | Secondary road traffic light controlling signal                                                                          |

// Output light mapping for MR_ctl and SR_ctl signals to be used 
// | Value (2bit binary)  | Light output                      |
// |----------------------|-----------------------------------|
// | 00                   | No light – traffic light is dark  |
// | 01                   | Red light                         |
// | 10                   | Yellow light                      |
// | 11                   | Green light                       |
//
// When rst is low, outputs should be dark, no light visible 
// When rst is high then: 
//     Minimum main road green period length should be at least 30 nanoseconds. When green period ends: 
//         If there are zero cars waiting on the secondary road, then main road starts the green state again 
//         If there are less than PARAMETER cars waiting on the secondary road, green period length is extended 
//         by 30 nanoseconds and then switches to red (and secondary to green) 
//         If there are equals/more than PARAMETER cars waiting on the secondary road, main road switches to red (and secondary to green) 
//     Secondary road green period length is 10 nanoseconds, after that, main road switches to green (and secondary to red) 
//     Each transition (red to green and green to red) should go through 3 nanoseconds yellow light. Yellow lights can happen at the same 
//     time in both traffic directions. 
// MR_ctl and SR_ctl both must not be green at the same time to avoid traffic accidents. 
// PARAMETER = 45.  
//
// Revision:
// A - initial design
// B - 
// C - 
//
///////////////////////////////////////////////////////////////////

module traffic_light_controller #( parameter
    PARAMETER	 = 45,
    MR_GREEN_TIME = 30-1, 
    SR_GREEN_TIME = 10-1,
    YELLOW_TIME = 3-1
)(
	input                                   clk,
	input                                   rst,
	input               [7:0]               MR_cars,
	output              [1:0]               MR_ctl,
	output              [1:0]               SR_ctl);

//-------------Internal Constants---------------------------
localparam      [2:0]   IDLE            = 'h0,
                        MR_GREEN_1      = 'h1,
                        MR_GREEN_2      = 'h2,
                        MR_YELLOW       = 'h3,
                        SR_GREEN        = 'h4,
                        SR_YELLOW       = 'h5;

//-------------Internal signals and components--------------
reg [2:0]               r_state = IDLE;
reg [4:0]               r_cnt = 'b0;
reg [1:0]               r_MR_ctl  = 'b0,
                        r_SR_ctl  = 'b0;

//------------ assignning combionational logic--------------

assign MR_ctl = r_MR_ctl;
assign SR_ctl = r_SR_ctl;

//----next state & outputs, combinational always block------
always@(posedge clk) begin
    if (rst) begin
    case(r_state)
        IDLE:  begin
            r_MR_ctl <= 'b00;
            r_SR_ctl <= 'b00;
            r_state <= MR_GREEN_1;
            r_cnt <= 'd0;
        end
        MR_GREEN_1:  begin
            r_MR_ctl <= 'b11;
            r_SR_ctl <= 'b01;
            if (r_cnt >= MR_GREEN_TIME) begin   
                if (MR_cars == 0) begin
                    r_cnt <= 0;
                    r_state <= MR_GREEN_1;
                    end
                else if (MR_cars < PARAMETER) begin
                    r_cnt <= 0;
                    r_state <= MR_GREEN_2;
                    end
                else if (MR_cars >= PARAMETER) begin
                    r_cnt <= 0;
                    r_state <= MR_YELLOW;
                    end  
                end
            else begin
                r_state <= MR_GREEN_1;
                r_cnt <= r_cnt + 1;
                end
        end
        MR_GREEN_2:  begin
            r_MR_ctl <= 'b11;
            r_SR_ctl <= 'b01;
            if (r_cnt >= MR_GREEN_TIME) begin
                r_cnt <= 0;
                r_state <= MR_YELLOW;
                end
            else begin
                r_cnt <= r_cnt + 1;
                r_state <= MR_GREEN_2;
                end
        end
        MR_YELLOW:  begin
            r_MR_ctl <= 'b10;
            r_SR_ctl <= 'b10;
            if (r_cnt >= YELLOW_TIME) begin
                r_cnt <= 0;
                r_state <= SR_GREEN;
                end
            else begin
                r_cnt <= r_cnt + 1;
                r_state <= MR_YELLOW;
                end
        end
        SR_GREEN:  begin
            r_MR_ctl <= 'b01;
            r_SR_ctl <= 'b11;
            if (r_cnt >= SR_GREEN_TIME) begin
                r_cnt <= 0;
                r_state <= SR_YELLOW;
                end
            else begin
                r_cnt <= r_cnt + 1;
                r_state <= SR_GREEN;
                end
        end
        SR_YELLOW:  begin
            r_MR_ctl <= 'b10;
            r_SR_ctl <= 'b10;
            if (r_cnt >= YELLOW_TIME) begin
                r_cnt = 0;
                r_state <= MR_GREEN_1;
                end
            else begin
                r_cnt <= r_cnt + 1;
                r_state <= SR_YELLOW;
                end
        end
        default: r_state <= IDLE;         // on error
    endcase
    end
    else begin
        r_state <= IDLE;
        r_MR_ctl <= 'b00;
        r_SR_ctl <= 'b00;
        r_cnt <= 0;
    end

end

endmodule

ps3/ps03q/tlc_tb.v
///////////////////////////////////////////////////////////////// 
// Author - Imants Pulkstenis
// Date - 23.02.2020
// Project name - PS03
// Module name - Testbench for Smart traffic light controler
//
// Detailed module description:
//
// Generating the stimulation 
// Clk - Generate the 1GHz clock input 
// Rst - generate both high and low reset to ensure correct start up, per Required functionality 
// MR_cars - generate multiple values to simulate real world traffic situation (e.g. at night some 
// cars arrive once per 60nanoseconds, in day – more cars) and verify that smart traffic light controller is working correctly. 
//
// The test can be executed using Icarus Verilog!
// The result can be evaluated in GTKwave application.  
// Code:
//     iverilog -o output.vvp tlc_tb.v && vvp output.vvp
//     gtkwave -f wave.vcd
//
// Revision:
// A - initial design
// B - 
// C - 
//
///////////////////////////////////////////////////////////////////

//UUT module
`include "traffic_light_controller.v"

// 1GHz clock -> 1ns period
// 50% duty cycle 0.5ns HIGH and 0.5ns LOW
// `timescale [time unit] / [time precision]
`timescale 1ns / 100ps

//define module 
module tlc_tb ();

//define inside use signals
reg         clk     = 1'b0;
reg         rst     = 1'b1;
reg [7:0]   MR_cars = 'b0;

integer ii=0;

//---------Test script----------------
// 50% duty cycle clock
always #0.5 clk <= ~clk;

//-----Unit Under test---------------
traffic_light_controller #(
        .PARAMETER(45)
) unit_under_test (
        .clk(clk),
        .rst(rst),
        .MR_cars(MR_cars),
        .MR_ctl(),
	    .SR_ctl());

//---------Reset Test--------------------
initial begin
    rst = 0;
    #10;
    rst = 1;
    #200
    rst = 0;
    #100;
    rst = 1;
    
end


initial
    begin
    //---------Daytime traffic Test--------------------
      for (ii=0; ii<50; ii=ii+1)
        begin
          MR_cars = ii;
          #10;
        end
      MR_cars = 0;
      #100;
      //---------Nighttime traffic Test--------------------
      for (ii=0; ii<50; ii=ii+1)
        begin
          MR_cars = ii;
          #60;
        end
      #100;
      $finish();
    end

// just print text 
initial begin 
    $display(" ");
    $display("----------------------------------------------");
    $display("          Starting Testbench...");
    $dumpfile("wave.vcd");
    $dumpvars(0);
    $display("----------------------------------------------");
    $display(" ");
end

endmodule

ps3/ps03q/wave.vcd
$date
	Mon Feb 24 00:17:16 2020
$end
$version
	Icarus Verilog
$end
$timescale
	100ps
$end
$scope module tlc_tb $end
$var reg 8 ! MR_cars [7:0] $end
$var reg 1 " clk $end
$var reg 1 # rst $end
$var integer 32 $ ii [31:0] $end
$scope module unit_under_test $end
$var wire 8 % MR_cars [7:0] $end
$var wire 2 & MR_ctl [1:0] $end
$var wire 2 ' SR_ctl [1:0] $end
$var wire 1 " clk $end
$var wire 1 # rst $end
$var reg 2 ( r_MR_ctl [1:0] $end
$var reg 2 ) r_SR_ctl [1:0] $end
$var reg 5 * r_cnt [4:0] $end
$var reg 3 + r_state [2:0] $end
$upscope $end
$upscope $end
$enddefinitions $end
#0
$dumpvars
b0 +
b0 *
b0 )
b0 (
b0 '
b0 &
b0 %
b0 $
0#
0"
b0 !
$end
#5
1"
#10
0"
#15
1"
#20
0"
#25
1"
#30
0"
#35
1"
#40
0"
#45
1"
#50
0"
#55
1"
#60
0"
#65
1"
#70
0"
#75
1"
#80
0"
#85
1"
#90
0"
#95
1"
#100
0"
b1 !
b1 %
b1 $
1#
#105
b1 +
1"
#110
0"
#115
b1 *
b1 '
b1 )
b11 &
b11 (
1"
#120
0"
#125
b10 *
1"
#130
0"
#135
b11 *
1"
#140
0"
#145
b100 *
1"
#150
0"
#155
b101 *
1"
#160
0"
#165
b110 *
1"
#170
0"
#175
b111 *
1"
#180
0"
#185
b1000 *
1"
#190
0"
#195
b1001 *
1"
#200
0"
b10 !
b10 %
b10 $
#205
b1010 *
1"
#210
0"
#215
b1011 *
1"
#220
0"
#225
b1100 *
1"
#230
0"
#235
b1101 *
1"
#240
0"
#245
b1110 *
1"
#250
0"
#255
b1111 *
1"
#260
0"
#265
b10000 *
1"
#270
0"
#275
b10001 *
1"
#280
0"
#285
b10010 *
1"
#290
0"
#295
b10011 *
1"
#300
0"
b11 !
b11 %
b11 $
#305
b10100 *
1"
#310
0"
#315
b10101 *
1"
#320
0"
#325
b10110 *
1"
#330
0"
#335
b10111 *
1"
#340
0"
#345
b11000 *
1"
#350
0"
#355
b11001 *
1"
#360
0"
#365
b11010 *
1"
#370
0"
#375
b11011 *
1"
#380
0"
#385
b11100 *
1"
#390
0"
#395
b11101 *
1"
#400
0"
b100 !
b100 %
b100 $
#405
b10 +
b0 *
1"
#410
0"
#415
b1 *
1"
#420
0"
#425
b10 *
1"
#430
0"
#435
b11 *
1"
#440
0"
#445
b100 *
1"
#450
0"
#455
b101 *
1"
#460
0"
#465
b110 *
1"
#470
0"
#475
b111 *
1"
#480
0"
#485
b1000 *
1"
#490
0"
#495
b1001 *
1"
#500
0"
b101 !
b101 %
b101 $
#505
b1010 *
1"
#510
0"
#515
b1011 *
1"
#520
0"
#525
b1100 *
1"
#530
0"
#535
b1101 *
1"
#540
0"
#545
b1110 *
1"
#550
0"
#555
b1111 *
1"
#560
0"
#565
b10000 *
1"
#570
0"
#575
b10001 *
1"
#580
0"
#585
b10010 *
1"
#590
0"
#595
b10011 *
1"
#600
0"
b110 !
b110 %
b110 $
#605
b10100 *
1"
#610
0"
#615
b10101 *
1"
#620
0"
#625
b10110 *
1"
#630
0"
#635
b10111 *
1"
#640
0"
#645
b11000 *
1"
#650
0"
#655
b11001 *
1"
#660
0"
#665
b11010 *
1"
#670
0"
#675
b11011 *
1"
#680
0"
#685
b11100 *
1"
#690
0"
#695
b11101 *
1"
#700
0"
b111 !
b111 %
b111 $
#705
b11 +
b0 *
1"
#710
0"
#715
b1 *
b10 '
b10 )
b10 &
b10 (
1"
#720
0"
#725
b10 *
1"
#730
0"
#735
b100 +
b0 *
1"
#740
0"
#745
b1 *
b11 '
b11 )
b1 &
b1 (
1"
#750
0"
#755
b10 *
1"
#760
0"
#765
b11 *
1"
#770
0"
#775
b100 *
1"
#780
0"
#785
b101 *
1"
#790
0"
#795
b110 *
1"
#800
0"
b1000 !
b1000 %
b1000 $
#805
b111 *
1"
#810
0"
#815
b1000 *
1"
#820
0"
#825
b1001 *
1"
#830
0"
#835
b101 +
b0 *
1"
#840
0"
#845
b1 *
b10 '
b10 )
b10 &
b10 (
1"
#850
0"
#855
b10 *
1"
#860
0"
#865
b1 +
b0 *
1"
#870
0"
#875
b1 *
b1 '
b1 )
b11 &
b11 (
1"
#880
0"
#885
b10 *
1"
#890
0"
#895
b11 *
1"
#900
0"
b1001 !
b1001 %
b1001 $
#905
b100 *
1"
#910
0"
#915
b101 *
1"
#920
0"
#925
b110 *
1"
#930
0"
#935
b111 *
1"
#940
0"
#945
b1000 *
1"
#950
0"
#955
b1001 *
1"
#960
0"
#965
b1010 *
1"
#970
0"
#975
b1011 *
1"
#980
0"
#985
b1100 *
1"
#990
0"
#995
b1101 *
1"
#1000
0"
b1010 !
b1010 %
b1010 $
#1005
b1110 *
1"
#1010
0"
#1015
b1111 *
1"
#1020
0"
#1025
b10000 *
1"
#1030
0"
#1035
b10001 *
1"
#1040
0"
#1045
b10010 *
1"
#1050
0"
#1055
b10011 *
1"
#1060
0"
#1065
b10100 *
1"
#1070
0"
#1075
b10101 *
1"
#1080
0"
#1085
b10110 *
1"
#1090
0"
#1095
b10111 *
1"
#1100
0"
b1011 !
b1011 %
b1011 $
#1105
b11000 *
1"
#1110
0"
#1115
b11001 *
1"
#1120
0"
#1125
b11010 *
1"
#1130
0"
#1135
b11011 *
1"
#1140
0"
#1145
b11100 *
1"
#1150
0"
#1155
b11101 *
1"
#1160
0"
#1165
b10 +
b0 *
1"
#1170
0"
#1175
b1 *
1"
#1180
0"
#1185
b10 *
1"
#1190
0"
#1195
b11 *
1"
#1200
0"
b1100 !
b1100 %
b1100 $
#1205
b100 *
1"
#1210
0"
#1215
b101 *
1"
#1220
0"
#1225
b110 *
1"
#1230
0"
#1235
b111 *
1"
#1240
0"
#1245
b1000 *
1"
#1250
0"
#1255
b1001 *
1"
#1260
0"
#1265
b1010 *
1"
#1270
0"
#1275
b1011 *
1"
#1280
0"
#1285
b1100 *
1"
#1290
0"
#1295
b1101 *
1"
#1300
0"
b1101 !
b1101 %
b1101 $
#1305
b1110 *
1"
#1310
0"
#1315
b1111 *
1"
#1320
0"
#1325
b10000 *
1"
#1330
0"
#1335
b10001 *
1"
#1340
0"
#1345
b10010 *
1"
#1350
0"
#1355
b10011 *
1"
#1360
0"
#1365
b10100 *
1"
#1370
0"
#1375
b10101 *
1"
#1380
0"
#1385
b10110 *
1"
#1390
0"
#1395
b10111 *
1"
#1400
0"
b1110 !
b1110 %
b1110 $
#1405
b11000 *
1"
#1410
0"
#1415
b11001 *
1"
#1420
0"
#1425
b11010 *
1"
#1430
0"
#1435
b11011 *
1"
#1440
0"
#1445
b11100 *
1"
#1450
0"
#1455
b11101 *
1"
#1460
0"
#1465
b11 +
b0 *
1"
#1470
0"
#1475
b1 *
b10 '
b10 )
b10 &
b10 (
1"
#1480
0"
#1485
b10 *
1"
#1490
0"
#1495
b100 +
b0 *
1"
#1500
0"
b1111 !
b1111 %
b1111 $
#1505
b1 *
b11 '
b11 )
b1 &
b1 (
1"
#1510
0"
#1515
b10 *
1"
#1520
0"
#1525
b11 *
1"
#1530
0"
#1535
b100 *
1"
#1540
0"
#1545
b101 *
1"
#1550
0"
#1555
b110 *
1"
#1560
0"
#1565
b111 *
1"
#1570
0"
#1575
b1000 *
1"
#1580
0"
#1585
b1001 *
1"
#1590
0"
#1595
b101 +
b0 *
1"
#1600
0"
b10000 !
b10000 %
b10000 $
#1605
b1 *
b10 '
b10 )
b10 &
b10 (
1"
#1610
0"
#1615
b10 *
1"
#1620
0"
#1625
b1 +
b0 *
1"
#1630
0"
#1635
b1 *
b1 '
b1 )
b11 &
b11 (
1"
#1640
0"
#1645
b10 *
1"
#1650
0"
#1655
b11 *
1"
#1660
0"
#1665
b100 *
1"
#1670
0"
#1675
b101 *
1"
#1680
0"
#1685
b110 *
1"
#1690
0"
#1695
b111 *
1"
#1700
0"
b10001 !
b10001 %
b10001 $
#1705
b1000 *
1"
#1710
0"
#1715
b1001 *
1"
#1720
0"
#1725
b1010 *
1"
#1730
0"
#1735
b1011 *
1"
#1740
0"
#1745
b1100 *
1"
#1750
0"
#1755
b1101 *
1"
#1760
0"
#1765
b1110 *
1"
#1770
0"
#1775
b1111 *
1"
#1780
0"
#1785
b10000 *
1"
#1790
0"
#1795
b10001 *
1"
#1800
0"
b10010 !
b10010 %
b10010 $
#1805
b10010 *
1"
#1810
0"
#1815
b10011 *
1"
#1820
0"
#1825
b10100 *
1"
#1830
0"
#1835
b10101 *
1"
#1840
0"
#1845
b10110 *
1"
#1850
0"
#1855
b10111 *
1"
#1860
0"
#1865
b11000 *
1"
#1870
0"
#1875
b11001 *
1"
#1880
0"
#1885
b11010 *
1"
#1890
0"
#1895
b11011 *
1"
#1900
0"
b10011 !
b10011 %
b10011 $
#1905
b11100 *
1"
#1910
0"
#1915
b11101 *
1"
#1920
0"
#1925
b10 +
b0 *
1"
#1930
0"
#1935
b1 *
1"
#1940
0"
#1945
b10 *
1"
#1950
0"
#1955
b11 *
1"
#1960
0"
#1965
b100 *
1"
#1970
0"
#1975
b101 *
1"
#1980
0"
#1985
b110 *
1"
#1990
0"
#1995
b111 *
1"
#2000
0"
b10100 !
b10100 %
b10100 $
#2005
b1000 *
1"
#2010
0"
#2015
b1001 *
1"
#2020
0"
#2025
b1010 *
1"
#2030
0"
#2035
b1011 *
1"
#2040
0"
#2045
b1100 *
1"
#2050
0"
#2055
b1101 *
1"
#2060
0"
#2065
b1110 *
1"
#2070
0"
#2075
b1111 *
1"
#2080
0"
#2085
b10000 *
1"
#2090
0"
#2095
b10001 *
1"
#2100
0"
b10101 !
b10101 %
b10101 $
0#
#2105
b0 *
b0 '
b0 )
b0 &
b0 (
b0 +
1"
#2110
0"
#2115
1"
#2120
0"
#2125
1"
#2130
0"
#2135
1"
#2140
0"
#2145
1"
#2150
0"
#2155
1"
#2160
0"
#2165
1"
#2170
0"
#2175
1"
#2180
0"
#2185
1"
#2190
0"
#2195
1"
#2200
0"
b10110 !
b10110 %
b10110 $
#2205
1"
#2210
0"
#2215
1"
#2220
0"
#2225
1"
#2230
0"
#2235
1"
#2240
0"
#2245
1"
#2250
0"
#2255
1"
#2260
0"
#2265
1"
#2270
0"
#2275
1"
#2280
0"
#2285
1"
#2290
0"
#2295
1"
#2300
0"
b10111 !
b10111 %
b10111 $
#2305
1"
#2310
0"
#2315
1"
#2320
0"
#2325
1"
#2330
0"
#2335
1"
#2340
0"
#2345
1"
#2350
0"
#2355
1"
#2360
0"
#2365
1"
#2370
0"
#2375
1"
#2380
0"
#2385
1"
#2390
0"
#2395
1"
#2400
0"
b11000 !
b11000 %
b11000 $
#2405
1"
#2410
0"
#2415
1"
#2420
0"
#2425
1"
#2430
0"
#2435
1"
#2440
0"
#2445
1"
#2450
0"
#2455
1"
#2460
0"
#2465
1"
#2470
0"
#2475
1"
#2480
0"
#2485
1"
#2490
0"
#2495
1"
#2500
0"
b11001 !
b11001 %
b11001 $
#2505
1"
#2510
0"
#2515
1"
#2520
0"
#2525
1"
#2530
0"
#2535
1"
#2540
0"
#2545
1"
#2550
0"
#2555
1"
#2560
0"
#2565
1"
#2570
0"
#2575
1"
#2580
0"
#2585
1"
#2590
0"
#2595
1"
#2600
0"
b11010 !
b11010 %
b11010 $
#2605
1"
#2610
0"
#2615
1"
#2620
0"
#2625
1"
#2630
0"
#2635
1"
#2640
0"
#2645
1"
#2650
0"
#2655
1"
#2660
0"
#2665
1"
#2670
0"
#2675
1"
#2680
0"
#2685
1"
#2690
0"
#2695
1"
#2700
0"
b11011 !
b11011 %
b11011 $
#2705
1"
#2710
0"
#2715
1"
#2720
0"
#2725
1"
#2730
0"
#2735
1"
#2740
0"
#2745
1"
#2750
0"
#2755
1"
#2760
0"
#2765
1"
#2770
0"
#2775
1"
#2780
0"
#2785
1"
#2790
0"
#2795
1"
#2800
0"
b11100 !
b11100 %
b11100 $
#2805
1"
#2810
0"
#2815
1"
#2820
0"
#2825
1"
#2830
0"
#2835
1"
#2840
0"
#2845
1"
#2850
0"
#2855
1"
#2860
0"
#2865
1"
#2870
0"
#2875
1"
#2880
0"
#2885
1"
#2890
0"
#2895
1"
#2900
0"
b11101 !
b11101 %
b11101 $
#2905
1"
#2910
0"
#2915
1"
#2920
0"
#2925
1"
#2930
0"
#2935
1"
#2940
0"
#2945
1"
#2950
0"
#2955
1"
#2960
0"
#2965
1"
#2970
0"
#2975
1"
#2980
0"
#2985
1"
#2990
0"
#2995
1"
#3000
0"
b11110 !
b11110 %
b11110 $
#3005
1"
#3010
0"
#3015
1"
#3020
0"
#3025
1"
#3030
0"
#3035
1"
#3040
0"
#3045
1"
#3050
0"
#3055
1"
#3060
0"
#3065
1"
#3070
0"
#3075
1"
#3080
0"
#3085
1"
#3090
0"
#3095
1"
#3100
0"
b11111 !
b11111 %
b11111 $
1#
#3105
b1 +
1"
#3110
0"
#3115
b1 *
b1 '
b1 )
b11 &
b11 (
1"
#3120
0"
#3125
b10 *
1"
#3130
0"
#3135
b11 *
1"
#3140
0"
#3145
b100 *
1"
#3150
0"
#3155
b101 *
1"
#3160
0"
#3165
b110 *
1"
#3170
0"
#3175
b111 *
1"
#3180
0"
#3185
b1000 *
1"
#3190
0"
#3195
b1001 *
1"
#3200
0"
b100000 !
b100000 %
b100000 $
#3205
b1010 *
1"
#3210
0"
#3215
b1011 *
1"
#3220
0"
#3225
b1100 *
1"
#3230
0"
#3235
b1101 *
1"
#3240
0"
#3245
b1110 *
1"
#3250
0"
#3255
b1111 *
1"
#3260
0"
#3265
b10000 *
1"
#3270
0"
#3275
b10001 *
1"
#3280
0"
#3285
b10010 *
1"
#3290
0"
#3295
b10011 *
1"
#3300
0"
b100001 !
b100001 %
b100001 $
#3305
b10100 *
1"
#3310
0"
#3315
b10101 *
1"
#3320
0"
#3325
b10110 *
1"
#3330
0"
#3335
b10111 *
1"
#3340
0"
#3345
b11000 *
1"
#3350
0"
#3355
b11001 *
1"
#3360
0"
#3365
b11010 *
1"
#3370
0"
#3375
b11011 *
1"
#3380
0"
#3385
b11100 *
1"
#3390
0"
#3395
b11101 *
1"
#3400
0"
b100010 !
b100010 %
b100010 $
#3405
b10 +
b0 *
1"
#3410
0"
#3415
b1 *
1"
#3420
0"
#3425
b10 *
1"
#3430
0"
#3435
b11 *
1"
#3440
0"
#3445
b100 *
1"
#3450
0"
#3455
b101 *
1"
#3460
0"
#3465
b110 *
1"
#3470
0"
#3475
b111 *
1"
#3480
0"
#3485
b1000 *
1"
#3490
0"
#3495
b1001 *
1"
#3500
0"
b100011 !
b100011 %
b100011 $
#3505
b1010 *
1"
#3510
0"
#3515
b1011 *
1"
#3520
0"
#3525
b1100 *
1"
#3530
0"
#3535
b1101 *
1"
#3540
0"
#3545
b1110 *
1"
#3550
0"
#3555
b1111 *
1"
#3560
0"
#3565
b10000 *
1"
#3570
0"
#3575
b10001 *
1"
#3580
0"
#3585
b10010 *
1"
#3590
0"
#3595
b10011 *
1"
#3600
0"
b100100 !
b100100 %
b100100 $
#3605
b10100 *
1"
#3610
0"
#3615
b10101 *
1"
#3620
0"
#3625
b10110 *
1"
#3630
0"
#3635
b10111 *
1"
#3640
0"
#3645
b11000 *
1"
#3650
0"
#3655
b11001 *
1"
#3660
0"
#3665
b11010 *
1"
#3670
0"
#3675
b11011 *
1"
#3680
0"
#3685
b11100 *
1"
#3690
0"
#3695
b11101 *
1"
#3700
0"
b100101 !
b100101 %
b100101 $
#3705
b11 +
b0 *
1"
#3710
0"
#3715
b1 *
b10 '
b10 )
b10 &
b10 (
1"
#3720
0"
#3725
b10 *
1"
#3730
0"
#3735
b100 +
b0 *
1"
#3740
0"
#3745
b1 *
b11 '
b11 )
b1 &
b1 (
1"
#3750
0"
#3755
b10 *
1"
#3760
0"
#3765
b11 *
1"
#3770
0"
#3775
b100 *
1"
#3780
0"
#3785
b101 *
1"
#3790
0"
#3795
b110 *
1"
#3800
0"
b100110 !
b100110 %
b100110 $
#3805
b111 *
1"
#3810
0"
#3815
b1000 *
1"
#3820
0"
#3825
b1001 *
1"
#3830
0"
#3835
b101 +
b0 *
1"
#3840
0"
#3845
b1 *
b10 '
b10 )
b10 &
b10 (
1"
#3850
0"
#3855
b10 *
1"
#3860
0"
#3865
b1 +
b0 *
1"
#3870
0"
#3875
b1 *
b1 '
b1 )
b11 &
b11 (
1"
#3880
0"
#3885
b10 *
1"
#3890
0"
#3895
b11 *
1"
#3900
0"
b100111 !
b100111 %
b100111 $
#3905
b100 *
1"
#3910
0"
#3915
b101 *
1"
#3920
0"
#3925
b110 *
1"
#3930
0"
#3935
b111 *
1"
#3940
0"
#3945
b1000 *
1"
#3950
0"
#3955
b1001 *
1"
#3960
0"
#3965
b1010 *
1"
#3970
0"
#3975
b1011 *
1"
#3980
0"
#3985
b1100 *
1"
#3990
0"
#3995
b1101 *
1"
#4000
0"
b101000 !
b101000 %
b101000 $
#4005
b1110 *
1"
#4010
0"
#4015
b1111 *
1"
#4020
0"
#4025
b10000 *
1"
#4030
0"
#4035
b10001 *
1"
#4040
0"
#4045
b10010 *
1"
#4050
0"
#4055
b10011 *
1"
#4060
0"
#4065
b10100 *
1"
#4070
0"
#4075
b10101 *
1"
#4080
0"
#4085
b10110 *
1"
#4090
0"
#4095
b10111 *
1"
#4100
0"
b101001 !
b101001 %
b101001 $
#4105
b11000 *
1"
#4110
0"
#4115
b11001 *
1"
#4120
0"
#4125
b11010 *
1"
#4130
0"
#4135
b11011 *
1"
#4140
0"
#4145
b11100 *
1"
#4150
0"
#4155
b11101 *
1"
#4160
0"
#4165
b10 +
b0 *
1"
#4170
0"
#4175
b1 *
1"
#4180
0"
#4185
b10 *
1"
#4190
0"
#4195
b11 *
1"
#4200
0"
b101010 !
b101010 %
b101010 $
#4205
b100 *
1"
#4210
0"
#4215
b101 *
1"
#4220
0"
#4225
b110 *
1"
#4230
0"
#4235
b111 *
1"
#4240
0"
#4245
b1000 *
1"
#4250
0"
#4255
b1001 *
1"
#4260
0"
#4265
b1010 *
1"
#4270
0"
#4275
b1011 *
1"
#4280
0"
#4285
b1100 *
1"
#4290
0"
#4295
b1101 *
1"
#4300
0"
b101011 !
b101011 %
b101011 $
#4305
b1110 *
1"
#4310
0"
#4315
b1111 *
1"
#4320
0"
#4325
b10000 *
1"
#4330
0"
#4335
b10001 *
1"
#4340
0"
#4345
b10010 *
1"
#4350
0"
#4355
b10011 *
1"
#4360
0"
#4365
b10100 *
1"
#4370
0"
#4375
b10101 *
1"
#4380
0"
#4385
b10110 *
1"
#4390
0"
#4395
b10111 *
1"
#4400
0"
b101100 !
b101100 %
b101100 $
#4405
b11000 *
1"
#4410
0"
#4415
b11001 *
1"
#4420
0"
#4425
b11010 *
1"
#4430
0"
#4435
b11011 *
1"
#4440
0"
#4445
b11100 *
1"
#4450
0"
#4455
b11101 *
1"
#4460
0"
#4465
b11 +
b0 *
1"
#4470
0"
#4475
b1 *
b10 '
b10 )
b10 &
b10 (
1"
#4480
0"
#4485
b10 *
1"
#4490
0"
#4495
b100 +
b0 *
1"
#4500
0"
b101101 !
b101101 %
b101101 $
#4505
b1 *
b11 '
b11 )
b1 &
b1 (
1"
#4510
0"
#4515
b10 *
1"
#4520
0"
#4525
b11 *
1"
#4530
0"
#4535
b100 *
1"
#4540
0"
#4545
b101 *
1"
#4550
0"
#4555
b110 *
1"
#4560
0"
#4565
b111 *
1"
#4570
0"
#4575
b1000 *
1"
#4580
0"
#4585
b1001 *
1"
#4590
0"
#4595
b101 +
b0 *
1"
#4600
0"
b101110 !
b101110 %
b101110 $
#4605
b1 *
b10 '
b10 )
b10 &
b10 (
1"
#4610
0"
#4615
b10 *
1"
#4620
0"
#4625
b1 +
b0 *
1"
#4630
0"
#4635
b1 *
b1 '
b1 )
b11 &
b11 (
1"
#4640
0"
#4645
b10 *
1"
#4650
0"
#4655
b11 *
1"
#4660
0"
#4665
b100 *
1"
#4670
0"
#4675
b101 *
1"
#4680
0"
#4685
b110 *
1"
#4690
0"
#4695
b111 *
1"
#4700
0"
b101111 !
b101111 %
b101111 $
#4705
b1000 *
1"
#4710
0"
#4715
b1001 *
1"
#4720
0"
#4725
b1010 *
1"
#4730
0"
#4735
b1011 *
1"
#4740
0"
#4745
b1100 *
1"
#4750
0"
#4755
b1101 *
1"
#4760
0"
#4765
b1110 *
1"
#4770
0"
#4775
b1111 *
1"
#4780
0"
#4785
b10000 *
1"
#4790
0"
#4795
b10001 *
1"
#4800
0"
b110000 !
b110000 %
b110000 $
#4805
b10010 *
1"
#4810
0"
#4815
b10011 *
1"
#4820
0"
#4825
b10100 *
1"
#4830
0"
#4835
b10101 *
1"
#4840
0"
#4845
b10110 *
1"
#4850
0"
#4855
b10111 *
1"
#4860
0"
#4865
b11000 *
1"
#4870
0"
#4875
b11001 *
1"
#4880
0"
#4885
b11010 *
1"
#4890
0"
#4895
b11011 *
1"
#4900
0"
b110001 !
b110001 %
b110001 $
#4905
b11100 *
1"
#4910
0"
#4915
b11101 *
1"
#4920
0"
#4925
b11 +
b0 *
1"
#4930
0"
#4935
b1 *
b10 '
b10 )
b10 &
b10 (
1"
#4940
0"
#4945
b10 *
1"
#4950
0"
#4955
b100 +
b0 *
1"
#4960
0"
#4965
b1 *
b11 '
b11 )
b1 &
b1 (
1"
#4970
0"
#4975
b10 *
1"
#4980
0"
#4985
b11 *
1"
#4990
0"
#4995
b100 *
1"
#5000
0"
b0 !
b0 %
b110010 $
#5005
b101 *
1"
#5010
0"
#5015
b110 *
1"
#5020
0"
#5025
b111 *
1"
#5030
0"
#5035
b1000 *
1"
#5040
0"
#5045
b1001 *
1"
#5050
0"
#5055
b101 +
b0 *
1"
#5060
0"
#5065
b1 *
b10 '
b10 )
b10 &
b10 (
1"
#5070
0"
#5075
b10 *
1"
#5080
0"
#5085
b1 +
b0 *
1"
#5090
0"
#5095
b1 *
b1 '
b1 )
b11 &
b11 (
1"
#5100
0"
#5105
b10 *
1"
#5110
0"
#5115
b11 *
1"
#5120
0"
#5125
b100 *
1"
#5130
0"
#5135
b101 *
1"
#5140
0"
#5145
b110 *
1"
#5150
0"
#5155
b111 *
1"
#5160
0"
#5165
b1000 *
1"
#5170
0"
#5175
b1001 *
1"
#5180
0"
#5185
b1010 *
1"
#5190
0"
#5195
b1011 *
1"
#5200
0"
#5205
b1100 *
1"
#5210
0"
#5215
b1101 *
1"
#5220
0"
#5225
b1110 *
1"
#5230
0"
#5235
b1111 *
1"
#5240
0"
#5245
b10000 *
1"
#5250
0"
#5255
b10001 *
1"
#5260
0"
#5265
b10010 *
1"
#5270
0"
#5275
b10011 *
1"
#5280
0"
#5285
b10100 *
1"
#5290
0"
#5295
b10101 *
1"
#5300
0"
#5305
b10110 *
1"
#5310
0"
